{"name":"Open Forms","id":"open-page-of-forms;open-forms","testSteps":[{"number":1,"description":"Given that the user opens the Forms page","duration":4670,"startTime":"2023-04-14T09:52:41.081-05:00[America/Bogota]","exception":{"errorType":"org.openqa.selenium.JavascriptException","message":"javascript error: Failed to set the \u0027innerHTML\u0027 property on \u0027Element\u0027: This document requires \u0027TrustedHTML\u0027 assignment.\n  (Session info: chrome\u003d112.0.5615.87)\nBuild info: version: \u00273.141.59\u0027, revision: \u0027e82be7d358\u0027, time: \u00272018-11-14T08:17:03\u0027\nSystem info: host: \u0027QV-3978\u0027, ip: \u0027192.168.99.109\u0027, os.name: \u0027Windows 10\u0027, os.arch: \u0027amd64\u0027, os.version: \u002710.0\u0027, java.version: \u00271.8.0_342\u0027\nDriver info: org.openqa.selenium.chrome.ChromeDriver\nCapabilities {acceptInsecureCerts: false, browserName: chrome, browserVersion: 112.0.5615.87, chrome: {chromedriverVersion: 111.0.5563.64 (c710e93d5b63..., userDataDir: C:\\Users\\SCASTA~1\\AppData\\L...}, goog:chromeOptions: {debuggerAddress: localhost:54981}, javascriptEnabled: true, networkConnectionEnabled: false, pageLoadStrategy: normal, platform: WINDOWS, platformName: WINDOWS, proxy: Proxy(), setWindowRect: true, strictFileInteractability: false, timeouts: {implicit: 0, pageLoad: 300000, script: 30000}, unhandledPromptBehavior: dismiss and notify, webauthn:extension:credBlob: true, webauthn:extension:largeBlob: true, webauthn:extension:minPinLength: true, webauthn:extension:prf: true, webauthn:virtualAuthenticators: true}\nSession ID: cc2c0c130608baca5b2b6d798732111d","stackTrace":[{"declaringClass":"com.co.forms.stepsdefinitions.OpenFormsStepDefinition","methodName":"thatTheUserOpensTheFormsPage","fileName":"OpenFormsStepDefinition.java","lineNumber":45},{"declaringClass":"cucumber.runner.Runner","methodName":"runPickle","fileName":"Runner.java","lineNumber":80}]},"result":"ERROR","precondition":false,"level":0,"children":[{"number":2,"description":"SARA opens the https://forms.gle/nSy3NyYchQa2JbP17","duration":4404,"startTime":"2023-04-14T09:52:41.319-05:00[America/Bogota]","screenshots":[{"screenshot":"56e17d7e06f228b01df826e73ff2e1401f7b1281c5808606738c73eb432adf54.png","htmlSource":"pagesource6083241256770195940.html.txt","timeStamp":1681483965713}],"exception":{"errorType":"org.openqa.selenium.JavascriptException","message":"javascript error: Failed to set the \u0027innerHTML\u0027 property on \u0027Element\u0027: This document requires \u0027TrustedHTML\u0027 assignment.\n  (Session info: chrome\u003d112.0.5615.87)\nBuild info: version: \u00273.141.59\u0027, revision: \u0027e82be7d358\u0027, time: \u00272018-11-14T08:17:03\u0027\nSystem info: host: \u0027QV-3978\u0027, ip: \u0027192.168.99.109\u0027, os.name: \u0027Windows 10\u0027, os.arch: \u0027amd64\u0027, os.version: \u002710.0\u0027, java.version: \u00271.8.0_342\u0027\nDriver info: org.openqa.selenium.chrome.ChromeDriver\nCapabilities {acceptInsecureCerts: false, browserName: chrome, browserVersion: 112.0.5615.87, chrome: {chromedriverVersion: 111.0.5563.64 (c710e93d5b63..., userDataDir: C:\\Users\\SCASTA~1\\AppData\\L...}, goog:chromeOptions: {debuggerAddress: localhost:54981}, javascriptEnabled: true, networkConnectionEnabled: false, pageLoadStrategy: normal, platform: WINDOWS, platformName: WINDOWS, proxy: Proxy(), setWindowRect: true, strictFileInteractability: false, timeouts: {implicit: 0, pageLoad: 300000, script: 30000}, unhandledPromptBehavior: dismiss and notify, webauthn:extension:credBlob: true, webauthn:extension:largeBlob: true, webauthn:extension:minPinLength: true, webauthn:extension:prf: true, webauthn:virtualAuthenticators: true}\nSession ID: cc2c0c130608baca5b2b6d798732111d","stackTrace":[{"declaringClass":"com.co.forms.stepsdefinitions.OpenFormsStepDefinition","methodName":"thatTheUserOpensTheFormsPage","fileName":"OpenFormsStepDefinition.java","lineNumber":45},{"declaringClass":"cucumber.runner.Runner","methodName":"runPickle","fileName":"Runner.java","lineNumber":80}]},"result":"ERROR","precondition":false,"level":1}]},{"number":3,"description":"When he fills in the fields B and clicks on the submit button\r\n| people |\r\n| 2 |","duration":23,"startTime":"2023-04-14T09:52:45.762-05:00[America/Bogota]","result":"SKIPPED","precondition":false,"level":0},{"number":4,"description":"Then he can check that he has correctly saved the answers","duration":11,"startTime":"2023-04-14T09:52:45.786-05:00[America/Bogota]","result":"SKIPPED","precondition":false,"level":0}],"userStory":{"id":"open-page-of-forms","storyName":"Open Page of Forms","path":"src/test/resources/features/open_forms.feature","narrative":"  I as user want open the page of Forms","type":"feature"},"featureTag":{"name":"Features/Open Page of Forms","type":"feature","displayName":"Features/Open Page of Forms"},"title":"Open Forms","tags":[{"name":"Open Page of Forms","type":"feature","displayName":"Open Page of Forms"}],"startTime":"2023-04-14T09:52:40.907-05:00[America/Bogota]","duration":4892,"testFailureCause":{"errorType":"org.openqa.selenium.JavascriptException","message":"javascript error: Failed to set the \u0027innerHTML\u0027 property on \u0027Element\u0027: This document requires \u0027TrustedHTML\u0027 assignment.\n  (Session info: chrome\u003d112.0.5615.87)\nBuild info: version: \u00273.141.59\u0027, revision: \u0027e82be7d358\u0027, time: \u00272018-11-14T08:17:03\u0027\nSystem info: host: \u0027QV-3978\u0027, ip: \u0027192.168.99.109\u0027, os.name: \u0027Windows 10\u0027, os.arch: \u0027amd64\u0027, os.version: \u002710.0\u0027, java.version: \u00271.8.0_342\u0027\nDriver info: org.openqa.selenium.chrome.ChromeDriver\nCapabilities {acceptInsecureCerts: false, browserName: chrome, browserVersion: 112.0.5615.87, chrome: {chromedriverVersion: 111.0.5563.64 (c710e93d5b63..., userDataDir: C:\\Users\\SCASTA~1\\AppData\\L...}, goog:chromeOptions: {debuggerAddress: localhost:54981}, javascriptEnabled: true, networkConnectionEnabled: false, pageLoadStrategy: normal, platform: WINDOWS, platformName: WINDOWS, proxy: Proxy(), setWindowRect: true, strictFileInteractability: false, timeouts: {implicit: 0, pageLoad: 300000, script: 30000}, unhandledPromptBehavior: dismiss and notify, webauthn:extension:credBlob: true, webauthn:extension:largeBlob: true, webauthn:extension:minPinLength: true, webauthn:extension:prf: true, webauthn:virtualAuthenticators: true}\nSession ID: cc2c0c130608baca5b2b6d798732111d","stackTrace":[{"declaringClass":"com.co.forms.stepsdefinitions.OpenFormsStepDefinition","methodName":"thatTheUserOpensTheFormsPage","fileName":"OpenFormsStepDefinition.java","lineNumber":45},{"declaringClass":"cucumber.runner.Runner","methodName":"runPickle","fileName":"Runner.java","lineNumber":80}]},"testFailureClassname":"org.openqa.selenium.JavascriptException","testFailureMessage":"javascript error: Failed to set the \u0027innerHTML\u0027 property on \u0027Element\u0027: This document requires \u0027TrustedHTML\u0027 assignment.\n  (Session info: chrome\u003d112.0.5615.87)\nBuild info: version: \u00273.141.59\u0027, revision: \u0027e82be7d358\u0027, time: \u00272018-11-14T08:17:03\u0027\nSystem info: host: \u0027QV-3978\u0027, ip: \u0027192.168.99.109\u0027, os.name: \u0027Windows 10\u0027, os.arch: \u0027amd64\u0027, os.version: \u002710.0\u0027, java.version: \u00271.8.0_342\u0027\nDriver info: org.openqa.selenium.chrome.ChromeDriver\nCapabilities {acceptInsecureCerts: false, browserName: chrome, browserVersion: 112.0.5615.87, chrome: {chromedriverVersion: 111.0.5563.64 (c710e93d5b63..., userDataDir: C:\\Users\\SCASTA~1\\AppData\\L...}, goog:chromeOptions: {debuggerAddress: localhost:54981}, javascriptEnabled: true, networkConnectionEnabled: false, pageLoadStrategy: normal, platform: WINDOWS, platformName: WINDOWS, proxy: Proxy(), setWindowRect: true, strictFileInteractability: false, timeouts: {implicit: 0, pageLoad: 300000, script: 30000}, unhandledPromptBehavior: dismiss and notify, webauthn:extension:credBlob: true, webauthn:extension:largeBlob: true, webauthn:extension:minPinLength: true, webauthn:extension:prf: true, webauthn:virtualAuthenticators: true}\nSession ID: cc2c0c130608baca5b2b6d798732111d","testFailureSummary":"ERROR;org.openqa.selenium.JavascriptException;javascript error: Failed to set the \u0027innerHTML\u0027 property on \u0027Element\u0027: This document requires \u0027TrustedHTML\u0027 assignment.\n  (Session info: chrome\u003d112.0.5615.87)\nBuild info: version: \u00273.141.59\u0027, revision: \u0027e82be7d358\u0027, time: \u00272018-11-14T08:17:03\u0027\nSystem info: host: \u0027QV-3978\u0027, ip: \u0027192.168.99.109\u0027, os.name: \u0027Windows 10\u0027, os.arch: \u0027amd64\u0027, os.version: \u002710.0\u0027, java.version: \u00271.8.0_342\u0027\nDriver info: org.openqa.selenium.chrome.ChromeDriver\nCapabilities {acceptInsecureCerts: false, browserName: chrome, browserVersion: 112.0.5615.87, chrome: {chromedriverVersion: 111.0.5563.64 (c710e93d5b63..., userDataDir: C:\\Users\\SCASTA~1\\AppData\\L...}, goog:chromeOptions: {debuggerAddress: localhost:54981}, javascriptEnabled: true, networkConnectionEnabled: false, pageLoadStrategy: normal, platform: WINDOWS, platformName: WINDOWS, proxy: Proxy(), setWindowRect: true, strictFileInteractability: false, timeouts: {implicit: 0, pageLoad: 300000, script: 30000}, unhandledPromptBehavior: dismiss and notify, webauthn:extension:credBlob: true, webauthn:extension:largeBlob: true, webauthn:extension:minPinLength: true, webauthn:extension:prf: true, webauthn:virtualAuthenticators: true}\nSession ID: cc2c0c130608baca5b2b6d798732111d;OpenFormsStepDefinition.java","projectKey":"","annotatedResult":"ERROR","sessionId":"cc2c0c130608baca5b2b6d798732111d","driver":"chrome:--start-maximized","isManualTestingUpToDate":false,"manual":false,"testSource":"Cucumber","actors":[{"name":"SARA","can":["browse the web"]}],"result":"ERROR"}